setup.py
odoo/addons/auto_save_extend/__init__.py
odoo/addons/auto_save_extend/__manifest__.py
odoo/addons/auto_save_extend/static/description/icon.png
odoo/addons/auto_save_extend/static/src/js/custom_confirmation_dialog.js
odoo/addons/auto_save_extend/static/src/js/form_controller.js
odoo/addons/auto_save_extend/static/src/js/list_controller.js
odoo/addons/auto_save_extend/static/src/js/menu_service.js
odoo/addons/auto_save_extend/static/src/xml/custom_confirmation_dialog.xml
odoo_addon_auto_save_extend.egg-info/PKG-INFO
odoo_addon_auto_save_extend.egg-info/SOURCES.txt
odoo_addon_auto_save_extend.egg-info/dependency_links.txt
odoo_addon_auto_save_extend.egg-info/not-zip-safe
odoo_addon_auto_save_extend.egg-info/requires.txt
odoo_addon_auto_save_extend.egg-info/top_level.txt