Metadata-Version: 2.1
Name: odoo-addon-auto-save-extend
Version: 16.0.1.0.0.5
Summary: Mejora el comportamiento de auto-guardado de Odoo con mejores diálogos y opciones
Home-page: https://somit.coop
Author: Som IT Cooperatiu SCCL
License: LGPL-3
Classifier: Programming Language :: Python
Classifier: Framework :: Odoo
Classifier: Framework :: Odoo :: 16.0
Classifier: License :: OSI Approved :: GNU Lesser General Public License v3 (LGPLv3)
Classifier: Development Status :: 4 - Beta
Requires-Python: >=3.10
